text_normalizer/__init__.py
text_normalizer/__version__.py
text_normalizer/base_text_normalizer.py
text_normalizer/base_text_normalizer_collection.py
text_normalizer/eng_lowercase_text_normalizer.py
text_normalizer/identity_text_normalizer.py
text_normalizer/number_token_text_normalizer.py
text_normalizer/punctuation_mapping_text_normalizer.py
text_normalizer/replace_pattern_with_token.py
text_normalizer/strip_text_normalizer.py
text_normalizer/collection/__init__.py
text_normalizer/collection/base_collection.py
text_normalizer/collection/basic.py
text_normalizer/collection/charactor.py
text_normalizer/collection/eng_basic.py
text_normalizer/collection/punctuation_keeping.py
text_normalizer/collection/unicode_mapping.py
text_normalizer/collection/test/__init__.py
text_normalizer/collection/test/test_base_collection.py
text_normalizer/collection/test/test_basic.py
text_normalizer/collection/test/test_charactor.py
text_normalizer/collection/test/test_eng_basic.py
text_normalizer/collection/test/test_punctuation_keeping.py
text_normalizer/collection/test/test_unicode_mapping.py
text_normalizer/data/punctuation/punctuation_mapping_0221.csv
text_normalizer/data/punctuation/punctuation_mapping_0221_simplified.csv
text_normalizer/data/unicode/chinese_characters_and_digits.txt
text_normalizer/data/unicode/chinese_characters_only.txt
text_normalizer/data/unicode/chinese_english_digits.txt
text_normalizer/data/unicode/chinese_english_digits_and_full_punctuations.txt
text_normalizer/data/unicode/chinese_english_digits_and_simplified_punctuations_1.txt
text_normalizer/data/unicode/english_characters_and_digits.txt
text_normalizer/data/unicode/english_digits_and_full_punctuations.txt
text_normalizer/factory/__init__.py
text_normalizer/factory/base_factory.py
text_normalizer/factory/eng_lowercase.py
text_normalizer/factory/identity.py
text_normalizer/factory/number_token.py
text_normalizer/factory/punctuation_mapping.py
text_normalizer-0.0.5.dist-info/METADATA
text_normalizer-0.0.5.dist-info/RECORD
text_normalizer-0.0.5.dist-info/WHEEL
text_normalizer-0.0.5.dist-info/top_level.txt
