Metadata-Version: 2.1
Name: text-normalizer
Version: 0.0.5
Summary: Yoctol Natural Language Text Normalizer
Home-page: UNKNOWN
Author: Solumilken
Author-email: UNKNOWN
License: MIT
Platform: UNKNOWN
Classifier: Programming Language :: Python
Classifier: Programming Language :: Python :: 3.5
Classifier: Programming Language :: Python :: 3.6
Requires-Dist: pandas (<0.21); python_version < "3.5"
Requires-Dist: pandas; python_version >= "3.5"
